{
    "704424": {
        "first_name": "Malinda",
        "middle_name": " N ",
        "last_name": "Fiack",
        "job_title": "EXECUTIVE DIRECTOR\/DELTA PROTECTION COMMISSION",
        "department": "DELTA PROTECTION COMMISSION",
        "base_pay": 0,
        "other_pay": 0,
        "overtime_pay": 0,
        "total_pay": 92705.96,
        "year": "-",
        "dept_average": 0
    },
    "856148": {
        "first_name": "Sheila",
        "middle_name": " A ",
        "last_name": "Singleton",
        "job_title": "ASSOCIATE GOVERNMENTAL PROGRAM ANALYST",
        "department": "DELTA PROTECTION COMMISSION",
        "base_pay": 0,
        "other_pay": 0,
        "overtime_pay": 0,
        "total_pay": 56368.5,
        "year": "-",
        "dept_average": 0
    },
    "1392241": {
        "first_name": "Judith",
        "middle_name": " L ",
        "last_name": "Quan",
        "job_title": "ENVIRONMENTAL PLANNER",
        "department": "DELTA PROTECTION COMMISSION",
        "base_pay": 0,
        "other_pay": 0,
        "overtime_pay": 0,
        "total_pay": 30674.46,
        "year": "-",
        "dept_average": 0
    },
    "1409022": {
        "first_name": "Alex",
        "middle_name": " R ",
        "last_name": "Westhoff",
        "job_title": "STUDENT ASSISTANT -ENGINEERING AND ARCHITECTURAL S",
        "department": "DELTA PROTECTION COMMISSION",
        "base_pay": 0,
        "other_pay": 0,
        "overtime_pay": 0,
        "total_pay": 17449.32,
        "year": "-",
        "dept_average": 0
    },
    "1395674": {
        "first_name": "Jessica",
        "middle_name": " ",
        "last_name": "Becerra",
        "job_title": "STUDENT ASSISTANT",
        "department": "DELTA PROTECTION COMMISSION",
        "base_pay": 0,
        "other_pay": 0,
        "overtime_pay": 0,
        "total_pay": 10985.98,
        "year": "-",
        "dept_average": 0
    }
}