{
    "2090733": {
        "first_name": "Stuart",
        "middle_name": "A",
        "last_name": "Drown",
        "job_title": "EXECUTIVE DIRECTOR, COMMISSION ON CALIFORNIA STATE GOVERNMENT ORGANIZATION AND ECONOMY",
        "department": "COMM ON STATE GOVT ORG & ECON",
        "base_pay": 0,
        "other_pay": 0,
        "overtime_pay": 0,
        "total_pay": 114265.2,
        "year": "-",
        "dept_average": 0
    },
    "2090732": {
        "first_name": "Carole",
        "middle_name": "J",
        "last_name": "D'elia",
        "job_title": "C.E.A.",
        "department": "COMM ON STATE GOVT ORG & ECON",
        "base_pay": 0,
        "other_pay": 0,
        "overtime_pay": 0,
        "total_pay": 87969.8,
        "year": "-",
        "dept_average": 0
    },
    "2090738": {
        "first_name": "Wayne",
        "middle_name": "",
        "last_name": "Davis",
        "job_title": "PROJECT MANAGER II, LITTLE HOOVER COMMISSION",
        "department": "COMM ON STATE GOVT ORG & ECON",
        "base_pay": 0,
        "other_pay": 0,
        "overtime_pay": 0,
        "total_pay": 75240.73,
        "year": "-",
        "dept_average": 0
    },
    "2090736": {
        "first_name": "James",
        "middle_name": "D",
        "last_name": "Wasserman",
        "job_title": "PROJECT MANAGER I, LITTLE HOOVER COMMISSION",
        "department": "COMM ON STATE GOVT ORG & ECON",
        "base_pay": 0,
        "other_pay": 0,
        "overtime_pay": 0,
        "total_pay": 67416.53,
        "year": "-",
        "dept_average": 0
    },
    "2090735": {
        "first_name": "Beth",
        "middle_name": "E",
        "last_name": "Miller",
        "job_title": "PROJECT MANAGER I, LITTLE HOOVER COMMISSION",
        "department": "COMM ON STATE GOVT ORG & ECON",
        "base_pay": 0,
        "other_pay": 0,
        "overtime_pay": 0,
        "total_pay": 58605.17,
        "year": "-",
        "dept_average": 0
    },
    "2090739": {
        "first_name": "David",
        "middle_name": "C",
        "last_name": "Brandt",
        "job_title": "STAFF SERVICES ANALYST (GENERAL)",
        "department": "COMM ON STATE GOVT ORG & ECON",
        "base_pay": 0,
        "other_pay": 0,
        "overtime_pay": 0,
        "total_pay": 51752.45,
        "year": "-",
        "dept_average": 0
    },
    "2090737": {
        "first_name": "Whitney",
        "middle_name": "E",
        "last_name": "Barazoto",
        "job_title": "PROJECT MANAGER II, LITTLE HOOVER COMMISSION",
        "department": "COMM ON STATE GOVT ORG & ECON",
        "base_pay": 0,
        "other_pay": 0,
        "overtime_pay": 0,
        "total_pay": 42261.85,
        "year": "-",
        "dept_average": 0
    },
    "2090740": {
        "first_name": "Sherry",
        "middle_name": "L",
        "last_name": "Mcalister",
        "job_title": "STAFF SERVICES ANALYST (GENERAL)",
        "department": "COMM ON STATE GOVT ORG & ECON",
        "base_pay": 0,
        "other_pay": 0,
        "overtime_pay": 0,
        "total_pay": 39407.63,
        "year": "-",
        "dept_average": 0
    },
    "2090734": {
        "first_name": "Tamar",
        "middle_name": "D",
        "last_name": "Foster",
        "job_title": "PROJECT MANAGER I, LITTLE HOOVER COMMISSION",
        "department": "COMM ON STATE GOVT ORG & ECON",
        "base_pay": 0,
        "other_pay": 0,
        "overtime_pay": 0,
        "total_pay": 31820.89,
        "year": "-",
        "dept_average": 0
    },
    "2090741": {
        "first_name": "Ciana",
        "middle_name": "",
        "last_name": "Gallardo",
        "job_title": "STUDENT ASSISTANT",
        "department": "COMM ON STATE GOVT ORG & ECON",
        "base_pay": 0,
        "other_pay": 0,
        "overtime_pay": 0,
        "total_pay": 2584.64,
        "year": "-",
        "dept_average": 0
    }
}