{
    "418077": {
        "first_name": "Jeffrey",
        "middle_name": " N ",
        "last_name": "Rudolph",
        "job_title": "C.E.A.",
        "department": "MUSEUM OF SCIENCE & INDUSTRY",
        "base_pay": 0,
        "other_pay": 0,
        "overtime_pay": 0,
        "total_pay": 126480,
        "year": "-",
        "dept_average": 0
    },
    "462416": {
        "first_name": "Cheryl",
        "middle_name": " N ",
        "last_name": "Tateishi",
        "job_title": "C.E.A.",
        "department": "MUSEUM OF SCIENCE & INDUSTRY",
        "base_pay": 0,
        "other_pay": 0,
        "overtime_pay": 0,
        "total_pay": 115281,
        "year": "-",
        "dept_average": 0
    },
    "516618": {
        "first_name": "Diane",
        "middle_name": " C ",
        "last_name": "Perlov",
        "job_title": "C.E.A.",
        "department": "MUSEUM OF SCIENCE & INDUSTRY",
        "base_pay": 0,
        "other_pay": 0,
        "overtime_pay": 0,
        "total_pay": 104745,
        "year": "-",
        "dept_average": 0
    },
    "518227": {
        "first_name": "Ronnie",
        "middle_name": " J ",
        "last_name": "Rohovit",
        "job_title": "DEPUTY DIRECTOR, EDUCATIONAL PROGRAMS, CALIFORNIA",
        "department": "MUSEUM OF SCIENCE & INDUSTRY",
        "base_pay": 0,
        "other_pay": 0,
        "overtime_pay": 0,
        "total_pay": 104424,
        "year": "-",
        "dept_average": 0
    },
    "522434": {
        "first_name": "Anthony",
        "middle_name": " G ",
        "last_name": "Budrovich",
        "job_title": "DEPUTY DIRECTOR FOR OPERATIONS",
        "department": "MUSEUM OF SCIENCE & INDUSTRY",
        "base_pay": 0,
        "other_pay": 0,
        "overtime_pay": 0,
        "total_pay": 104004,
        "year": "-",
        "dept_average": 0
    },
    "581179": {
        "first_name": "Eddie",
        "middle_name": " E ",
        "last_name": "Kouyoumdjian",
        "job_title": "EXPOSITION PARK MANAGER",
        "department": "MUSEUM OF SCIENCE & INDUSTRY",
        "base_pay": 0,
        "other_pay": 0,
        "overtime_pay": 0,
        "total_pay": 89598,
        "year": "-",
        "dept_average": 0
    },
    "685421": {
        "first_name": "Nathan",
        "middle_name": " ",
        "last_name": "Miranda",
        "job_title": "MANAGER OF EXHIBIT SERVICES",
        "department": "MUSEUM OF SCIENCE & INDUSTRY",
        "base_pay": 0,
        "other_pay": 0,
        "overtime_pay": 0,
        "total_pay": 89064,
        "year": "-",
        "dept_average": 0
    },
    "625872": {
        "first_name": "Kenneth",
        "middle_name": " E ",
        "last_name": "Phillips",
        "job_title": "ADMINISTRATOR, SCIENCE PROGRAM, CALIFORNIA SCIENCE",
        "department": "MUSEUM OF SCIENCE & INDUSTRY",
        "base_pay": 0,
        "other_pay": 0,
        "overtime_pay": 0,
        "total_pay": 88740,
        "year": "-",
        "dept_average": 0
    },
    "625869": {
        "first_name": "Charles",
        "middle_name": " D ",
        "last_name": "Kopczak",
        "job_title": "ADMINISTRATOR, SCIENCE PROGRAM, CALIFORNIA SCIENCE",
        "department": "MUSEUM OF SCIENCE & INDUSTRY",
        "base_pay": 0,
        "other_pay": 0,
        "overtime_pay": 0,
        "total_pay": 88740,
        "year": "-",
        "dept_average": 0
    },
    "625866": {
        "first_name": "David",
        "middle_name": " ",
        "last_name": "Bibas",
        "job_title": "ADMINISTRATOR, INDUSTRIAL EDUCATION PROGRAM, CALIF",
        "department": "MUSEUM OF SCIENCE & INDUSTRY",
        "base_pay": 0,
        "other_pay": 0,
        "overtime_pay": 0,
        "total_pay": 88740,
        "year": "-",
        "dept_average": 0
    },
    "968432": {
        "first_name": "Krisztina",
        "middle_name": " ",
        "last_name": "Eleki",
        "job_title": "ADMINISTRATOR, SCIENCE PROGRAM, CALIFORNIA SCIENCE",
        "department": "MUSEUM OF SCIENCE & INDUSTRY",
        "base_pay": 0,
        "other_pay": 0,
        "overtime_pay": 0,
        "total_pay": 80484,
        "year": "-",
        "dept_average": 0
    },
    "685418": {
        "first_name": "Peter",
        "middle_name": " J ",
        "last_name": "Lopez",
        "job_title": "STAFF SERVICES MANAGER II (SUPERVISORY)",
        "department": "MUSEUM OF SCIENCE & INDUSTRY",
        "base_pay": 0,
        "other_pay": 0,
        "overtime_pay": 0,
        "total_pay": 77490,
        "year": "-",
        "dept_average": 0
    },
    "762555": {
        "first_name": "Ricardo",
        "middle_name": " ",
        "last_name": "Mora",
        "job_title": "MUSEUM ELECTRICIAN",
        "department": "MUSEUM OF SCIENCE & INDUSTRY",
        "base_pay": 0,
        "other_pay": 0,
        "overtime_pay": 0,
        "total_pay": 74832.12,
        "year": "-",
        "dept_average": 0
    },
    "738743": {
        "first_name": "Froylan",
        "middle_name": " S ",
        "last_name": "Morales",
        "job_title": "CHIEF OF PLANT OPERATION III",
        "department": "MUSEUM OF SCIENCE & INDUSTRY",
        "base_pay": 0,
        "other_pay": 0,
        "overtime_pay": 0,
        "total_pay": 74802,
        "year": "-",
        "dept_average": 0
    },
    "782773": {
        "first_name": "Seana",
        "middle_name": " M ",
        "last_name": "Campos",
        "job_title": "FISCAL OFFICER I",
        "department": "MUSEUM OF SCIENCE & INDUSTRY",
        "base_pay": 0,
        "other_pay": 0,
        "overtime_pay": 0,
        "total_pay": 71017.12,
        "year": "-",
        "dept_average": 0
    },
    "892062": {
        "first_name": "Johel",
        "middle_name": " E ",
        "last_name": "Moran",
        "job_title": "STATIONARY ENGINEER",
        "department": "MUSEUM OF SCIENCE & INDUSTRY",
        "base_pay": 0,
        "other_pay": 0,
        "overtime_pay": 0,
        "total_pay": 69747.16,
        "year": "-",
        "dept_average": 0
    },
    "772737": {
        "first_name": "Nathan",
        "middle_name": " J ",
        "last_name": "Francis",
        "job_title": "CHIEF OF PLANT OPERATION I",
        "department": "MUSEUM OF SCIENCE & INDUSTRY",
        "base_pay": 0,
        "other_pay": 0,
        "overtime_pay": 0,
        "total_pay": 69696,
        "year": "-",
        "dept_average": 0
    },
    "822075": {
        "first_name": "Chris",
        "middle_name": " D ",
        "last_name": "Stokes",
        "job_title": "CHIEF ENGINEER II",
        "department": "MUSEUM OF SCIENCE & INDUSTRY",
        "base_pay": 0,
        "other_pay": 0,
        "overtime_pay": 0,
        "total_pay": 69508.98,
        "year": "-",
        "dept_average": 0
    },
    "952446": {
        "first_name": "Stephen",
        "middle_name": " A ",
        "last_name": "Lewis",
        "job_title": "MUSEUM SECURITY OFFICER",
        "department": "MUSEUM OF SCIENCE & INDUSTRY",
        "base_pay": 0,
        "other_pay": 0,
        "overtime_pay": 0,
        "total_pay": 69292.15,
        "year": "-",
        "dept_average": 0
    },
    "942301": {
        "first_name": "Kenneth",
        "middle_name": " W ",
        "last_name": "Williams",
        "job_title": "SUPERVISING MUSEUM SECURITY OFFICER",
        "department": "MUSEUM OF SCIENCE & INDUSTRY",
        "base_pay": 0,
        "other_pay": 0,
        "overtime_pay": 0,
        "total_pay": 68950.44,
        "year": "-",
        "dept_average": 0
    },
    "811475": {
        "first_name": "Carl",
        "middle_name": " L ",
        "last_name": "Phillips",
        "job_title": "CHIEF OF PLANT OPERATION I",
        "department": "MUSEUM OF SCIENCE & INDUSTRY",
        "base_pay": 0,
        "other_pay": 0,
        "overtime_pay": 0,
        "total_pay": 68364,
        "year": "-",
        "dept_average": 0
    },
    "860986": {
        "first_name": "Jesus",
        "middle_name": " A ",
        "last_name": "Castillo",
        "job_title": "MUSEUM SECURITY OFFICER",
        "department": "MUSEUM OF SCIENCE & INDUSTRY",
        "base_pay": 0,
        "other_pay": 0,
        "overtime_pay": 0,
        "total_pay": 67587.96,
        "year": "-",
        "dept_average": 0
    },
    "1082887": {
        "first_name": "Larry",
        "middle_name": " ",
        "last_name": "Pena",
        "job_title": "MUSEUM SECURITY OFFICER",
        "department": "MUSEUM OF SCIENCE & INDUSTRY",
        "base_pay": 0,
        "other_pay": 0,
        "overtime_pay": 0,
        "total_pay": 67423.08,
        "year": "-",
        "dept_average": 0
    },
    "899727": {
        "first_name": "Steven",
        "middle_name": " S ",
        "last_name": "Chung",
        "job_title": "STATIONARY ENGINEER",
        "department": "MUSEUM OF SCIENCE & INDUSTRY",
        "base_pay": 0,
        "other_pay": 0,
        "overtime_pay": 0,
        "total_pay": 65287.77,
        "year": "-",
        "dept_average": 0
    },
    "936215": {
        "first_name": "Leroy",
        "middle_name": " ",
        "last_name": "Ward",
        "job_title": "STATIONARY ENGINEER",
        "department": "MUSEUM OF SCIENCE & INDUSTRY",
        "base_pay": 0,
        "other_pay": 0,
        "overtime_pay": 0,
        "total_pay": 63966.85,
        "year": "-",
        "dept_average": 0
    },
    "930183": {
        "first_name": "Eligio",
        "middle_name": " D ",
        "last_name": "Umayam",
        "job_title": "STATIONARY ENGINEER",
        "department": "MUSEUM OF SCIENCE & INDUSTRY",
        "base_pay": 0,
        "other_pay": 0,
        "overtime_pay": 0,
        "total_pay": 63263.78,
        "year": "-",
        "dept_average": 0
    },
    "928972": {
        "first_name": "Sergio",
        "middle_name": " ",
        "last_name": "Farfan",
        "job_title": "STATIONARY ENGINEER",
        "department": "MUSEUM OF SCIENCE & INDUSTRY",
        "base_pay": 0,
        "other_pay": 0,
        "overtime_pay": 0,
        "total_pay": 62912.96,
        "year": "-",
        "dept_average": 0
    },
    "936312": {
        "first_name": "David",
        "middle_name": " ",
        "last_name": "Meza",
        "job_title": "STATIONARY ENGINEER",
        "department": "MUSEUM OF SCIENCE & INDUSTRY",
        "base_pay": 0,
        "other_pay": 0,
        "overtime_pay": 0,
        "total_pay": 61516.78,
        "year": "-",
        "dept_average": 0
    },
    "831289": {
        "first_name": "Patricia",
        "middle_name": " ",
        "last_name": "Marquez",
        "job_title": "RESEARCH MANAGER I -GENERAL-",
        "department": "MUSEUM OF SCIENCE & INDUSTRY",
        "base_pay": 0,
        "other_pay": 0,
        "overtime_pay": 0,
        "total_pay": 61005.67,
        "year": "-",
        "dept_average": 0
    },
    "971359": {
        "first_name": "Jeremy",
        "middle_name": " S ",
        "last_name": "Stoller",
        "job_title": "GRAPHIC DESIGNER II",
        "department": "MUSEUM OF SCIENCE & INDUSTRY",
        "base_pay": 0,
        "other_pay": 0,
        "overtime_pay": 0,
        "total_pay": 59920.47,
        "year": "-",
        "dept_average": 0
    },
    "869955": {
        "first_name": "Henry",
        "middle_name": " R ",
        "last_name": "Fimbres",
        "job_title": "ASSISTANT CHIEF, MUSEUM SECURITY AND SAFETY, CALIF",
        "department": "MUSEUM OF SCIENCE & INDUSTRY",
        "base_pay": 0,
        "other_pay": 0,
        "overtime_pay": 0,
        "total_pay": 58850.95,
        "year": "-",
        "dept_average": 0
    },
    "994828": {
        "first_name": "Nathaniel",
        "middle_name": " ",
        "last_name": "Smith",
        "job_title": "MUSEUM SECURITY OFFICER",
        "department": "MUSEUM OF SCIENCE & INDUSTRY",
        "base_pay": 0,
        "other_pay": 0,
        "overtime_pay": 0,
        "total_pay": 58614.44,
        "year": "-",
        "dept_average": 0
    },
    "873373": {
        "first_name": "Kathryn",
        "middle_name": " A ",
        "last_name": "Marsailes",
        "job_title": "EXHIBIT DESIGNER\/COORDINATOR",
        "department": "MUSEUM OF SCIENCE & INDUSTRY",
        "base_pay": 0,
        "other_pay": 0,
        "overtime_pay": 0,
        "total_pay": 58320,
        "year": "-",
        "dept_average": 0
    },
    "1036219": {
        "first_name": "Loc",
        "middle_name": " T ",
        "last_name": "Huynh",
        "job_title": "EXHIBIT ELECTRONICS TECHNICIAN, CALIFORNIA MUSEUM",
        "department": "MUSEUM OF SCIENCE & INDUSTRY",
        "base_pay": 0,
        "other_pay": 0,
        "overtime_pay": 0,
        "total_pay": 58176.07,
        "year": "-",
        "dept_average": 0
    },
    "977010": {
        "first_name": "Pauline",
        "middle_name": " A ",
        "last_name": "Obioha",
        "job_title": "ACCOUNTING OFFICER (SUPERVISOR)",
        "department": "MUSEUM OF SCIENCE & INDUSTRY",
        "base_pay": 0,
        "other_pay": 0,
        "overtime_pay": 0,
        "total_pay": 56767.38,
        "year": "-",
        "dept_average": 0
    },
    "1312048": {
        "first_name": "Dorothy",
        "middle_name": " Mae ",
        "last_name": "Vick",
        "job_title": "MUSEUM SECURITY OFFICER",
        "department": "MUSEUM OF SCIENCE & INDUSTRY",
        "base_pay": 0,
        "other_pay": 0,
        "overtime_pay": 0,
        "total_pay": 56425.66,
        "year": "-",
        "dept_average": 0
    },
    "1079550": {
        "first_name": "Herman",
        "middle_name": " A ",
        "last_name": "Watson",
        "job_title": "MUSEUM SECURITY OFFICER",
        "department": "MUSEUM OF SCIENCE & INDUSTRY",
        "base_pay": 0,
        "other_pay": 0,
        "overtime_pay": 0,
        "total_pay": 54112.36,
        "year": "-",
        "dept_average": 0
    },
    "860078": {
        "first_name": "David",
        "middle_name": " A ",
        "last_name": "Smitson",
        "job_title": "PLUMBER SUPERVISOR",
        "department": "MUSEUM OF SCIENCE & INDUSTRY",
        "base_pay": 0,
        "other_pay": 0,
        "overtime_pay": 0,
        "total_pay": 53532.83,
        "year": "-",
        "dept_average": 0
    },
    "1217241": {
        "first_name": "Noah",
        "middle_name": " ",
        "last_name": "Williams Jr",
        "job_title": "ELECTRICIAN II",
        "department": "MUSEUM OF SCIENCE & INDUSTRY",
        "base_pay": 0,
        "other_pay": 0,
        "overtime_pay": 0,
        "total_pay": 52862.1,
        "year": "-",
        "dept_average": 0
    },
    "1032230": {
        "first_name": "Scott",
        "middle_name": " W ",
        "last_name": "Buckler",
        "job_title": "EXHIBIT ELECTRONICS TECHNICIAN, CALIFORNIA MUSEUM",
        "department": "MUSEUM OF SCIENCE & INDUSTRY",
        "base_pay": 0,
        "other_pay": 0,
        "overtime_pay": 0,
        "total_pay": 52647.36,
        "year": "-",
        "dept_average": 0
    },
    "1085484": {
        "first_name": "Anthony",
        "middle_name": " R ",
        "last_name": "Olazabal",
        "job_title": "EXHIBIT DESIGNER-INSTALLER",
        "department": "MUSEUM OF SCIENCE & INDUSTRY",
        "base_pay": 0,
        "other_pay": 0,
        "overtime_pay": 0,
        "total_pay": 52331.04,
        "year": "-",
        "dept_average": 0
    },
    "1093323": {
        "first_name": "Damion",
        "middle_name": " A ",
        "last_name": "Lawrence",
        "job_title": "MUSEUM SECURITY OFFICER",
        "department": "MUSEUM OF SCIENCE & INDUSTRY",
        "base_pay": 0,
        "other_pay": 0,
        "overtime_pay": 0,
        "total_pay": 51852.23,
        "year": "-",
        "dept_average": 0
    },
    "1010770": {
        "first_name": "Brian",
        "middle_name": " R ",
        "last_name": "Stotesbery",
        "job_title": "EXHIBIT ELECTRONICS TECHNICIAN, CALIFORNIA MUSEUM",
        "department": "MUSEUM OF SCIENCE & INDUSTRY",
        "base_pay": 0,
        "other_pay": 0,
        "overtime_pay": 0,
        "total_pay": 51733.01,
        "year": "-",
        "dept_average": 0
    },
    "1031415": {
        "first_name": "Richard",
        "middle_name": " ",
        "last_name": "Jimenez",
        "job_title": "MAINTENANCE MECHANIC",
        "department": "MUSEUM OF SCIENCE & INDUSTRY",
        "base_pay": 0,
        "other_pay": 0,
        "overtime_pay": 0,
        "total_pay": 51605.24,
        "year": "-",
        "dept_average": 0
    },
    "1023955": {
        "first_name": "Hugo",
        "middle_name": " I ",
        "last_name": "Nunez",
        "job_title": "CARPENTER II",
        "department": "MUSEUM OF SCIENCE & INDUSTRY",
        "base_pay": 0,
        "other_pay": 0,
        "overtime_pay": 0,
        "total_pay": 51605,
        "year": "-",
        "dept_average": 0
    },
    "1143677": {
        "first_name": "Benedicto",
        "middle_name": " N ",
        "last_name": "Bambico",
        "job_title": "ELECTRICIAN I",
        "department": "MUSEUM OF SCIENCE & INDUSTRY",
        "base_pay": 0,
        "other_pay": 0,
        "overtime_pay": 0,
        "total_pay": 51448.26,
        "year": "-",
        "dept_average": 0
    },
    "967724": {
        "first_name": "Francisco",
        "middle_name": " ",
        "last_name": "Hernandez",
        "job_title": "EXHIBIT ELECTRONICS SUPERVISOR, CALIFORNIA MUSEUM",
        "department": "MUSEUM OF SCIENCE & INDUSTRY",
        "base_pay": 0,
        "other_pay": 0,
        "overtime_pay": 0,
        "total_pay": 51340.36,
        "year": "-",
        "dept_average": 0
    },
    "1066224": {
        "first_name": "Michael",
        "middle_name": " A ",
        "last_name": "Rincon",
        "job_title": "PLUMBER I",
        "department": "MUSEUM OF SCIENCE & INDUSTRY",
        "base_pay": 0,
        "other_pay": 0,
        "overtime_pay": 0,
        "total_pay": 51139.2,
        "year": "-",
        "dept_average": 0
    },
    "1029807": {
        "first_name": "Alex",
        "middle_name": " R ",
        "last_name": "Perez",
        "job_title": "ELECTRICIAN I",
        "department": "MUSEUM OF SCIENCE & INDUSTRY",
        "base_pay": 0,
        "other_pay": 0,
        "overtime_pay": 0,
        "total_pay": 51084.66,
        "year": "-",
        "dept_average": 0
    },
    "1031064": {
        "first_name": "Randy",
        "middle_name": " D ",
        "last_name": "Tirazona",
        "job_title": "EXHIBIT ELECTRONICS TECHNICIAN, CALIFORNIA MUSEUM",
        "department": "MUSEUM OF SCIENCE & INDUSTRY",
        "base_pay": 0,
        "other_pay": 0,
        "overtime_pay": 0,
        "total_pay": 50818.46,
        "year": "-",
        "dept_average": 0
    },
    "1093584": {
        "first_name": "Sheryl",
        "middle_name": " ",
        "last_name": "Oates-Hackett",
        "job_title": "EXHIBIT ELECTRONICS TECHNICIAN, CALIFORNIA MUSEUM",
        "department": "MUSEUM OF SCIENCE & INDUSTRY",
        "base_pay": 0,
        "other_pay": 0,
        "overtime_pay": 0,
        "total_pay": 50785.83,
        "year": "-",
        "dept_average": 0
    },
    "1011214": {
        "first_name": "Clarence",
        "middle_name": " K ",
        "last_name": "Aston",
        "job_title": "PLUMBER I",
        "department": "MUSEUM OF SCIENCE & INDUSTRY",
        "base_pay": 0,
        "other_pay": 0,
        "overtime_pay": 0,
        "total_pay": 50491.95,
        "year": "-",
        "dept_average": 0
    },
    "1370610": {
        "first_name": "Huey",
        "middle_name": " L ",
        "last_name": "Wynn",
        "job_title": "MAINTENANCE MECHANIC",
        "department": "MUSEUM OF SCIENCE & INDUSTRY",
        "base_pay": 0,
        "other_pay": 0,
        "overtime_pay": 0,
        "total_pay": 50484,
        "year": "-",
        "dept_average": 0
    },
    "1061396": {
        "first_name": "George",
        "middle_name": " ",
        "last_name": "Phillipsiii",
        "job_title": "MUSEUM SECURITY OFFICER",
        "department": "MUSEUM OF SCIENCE & INDUSTRY",
        "base_pay": 0,
        "other_pay": 0,
        "overtime_pay": 0,
        "total_pay": 50124.41,
        "year": "-",
        "dept_average": 0
    },
    "1371325": {
        "first_name": "Loren",
        "middle_name": " C ",
        "last_name": "Smith",
        "job_title": "CAPITAL OUTLAY PROGRAM MANAGER",
        "department": "MUSEUM OF SCIENCE & INDUSTRY",
        "base_pay": 0,
        "other_pay": 0,
        "overtime_pay": 0,
        "total_pay": 49582.36,
        "year": "-",
        "dept_average": 0
    },
    "897958": {
        "first_name": "Serafin",
        "middle_name": " A ",
        "last_name": "Santa Maria",
        "job_title": "STATIONARY ENGINEER",
        "department": "MUSEUM OF SCIENCE & INDUSTRY",
        "base_pay": 0,
        "other_pay": 0,
        "overtime_pay": 0,
        "total_pay": 49365.29,
        "year": "-",
        "dept_average": 0
    },
    "1073354": {
        "first_name": "David",
        "middle_name": " N ",
        "last_name": "Johnson",
        "job_title": "SUPERVISING MUSEUM SECURITY OFFICER",
        "department": "MUSEUM OF SCIENCE & INDUSTRY",
        "base_pay": 0,
        "other_pay": 0,
        "overtime_pay": 0,
        "total_pay": 49300,
        "year": "-",
        "dept_average": 0
    },
    "1091717": {
        "first_name": "Brandon",
        "middle_name": " D ",
        "last_name": "Williams",
        "job_title": "AUDIO-VISUAL TECHNICIAN, CALIFORNIA MUSEUM OF SCIE",
        "department": "MUSEUM OF SCIENCE & INDUSTRY",
        "base_pay": 0,
        "other_pay": 0,
        "overtime_pay": 0,
        "total_pay": 48986.42,
        "year": "-",
        "dept_average": 0
    },
    "1059967": {
        "first_name": "Shamalar",
        "middle_name": " A ",
        "last_name": "Fields",
        "job_title": "MUSEUM SECURITY OFFICER",
        "department": "MUSEUM OF SCIENCE & INDUSTRY",
        "base_pay": 0,
        "other_pay": 0,
        "overtime_pay": 0,
        "total_pay": 48803.05,
        "year": "-",
        "dept_average": 0
    },
    "1037830": {
        "first_name": "Maria",
        "middle_name": " G ",
        "last_name": "Hill",
        "job_title": "PERSONNEL SPECIALIST",
        "department": "MUSEUM OF SCIENCE & INDUSTRY",
        "base_pay": 0,
        "other_pay": 0,
        "overtime_pay": 0,
        "total_pay": 48639.28,
        "year": "-",
        "dept_average": 0
    },
    "1029915": {
        "first_name": "Cristina",
        "middle_name": " D ",
        "last_name": "Fernandez",
        "job_title": "BUSINESS SERVICE OFFICER I (SPECIALIST)",
        "department": "MUSEUM OF SCIENCE & INDUSTRY",
        "base_pay": 0,
        "other_pay": 0,
        "overtime_pay": 0,
        "total_pay": 48408,
        "year": "-",
        "dept_average": 0
    },
    "1086830": {
        "first_name": "John",
        "middle_name": " E ",
        "last_name": "Garvin",
        "job_title": "PAINTER I",
        "department": "MUSEUM OF SCIENCE & INDUSTRY",
        "base_pay": 0,
        "other_pay": 0,
        "overtime_pay": 0,
        "total_pay": 48260.4,
        "year": "-",
        "dept_average": 0
    },
    "1058087": {
        "first_name": "Cletton",
        "middle_name": " ",
        "last_name": "Jourdan",
        "job_title": "MUSEUM SECURITY OFFICER",
        "department": "MUSEUM OF SCIENCE & INDUSTRY",
        "base_pay": 0,
        "other_pay": 0,
        "overtime_pay": 0,
        "total_pay": 48200.79,
        "year": "-",
        "dept_average": 0
    },
    "1183522": {
        "first_name": "Darryl",
        "middle_name": " ",
        "last_name": "Collins",
        "job_title": "PAINTER I",
        "department": "MUSEUM OF SCIENCE & INDUSTRY",
        "base_pay": 0,
        "other_pay": 0,
        "overtime_pay": 0,
        "total_pay": 48167.28,
        "year": "-",
        "dept_average": 0
    },
    "1063509": {
        "first_name": "Manuel",
        "middle_name": " ",
        "last_name": "Villanueva",
        "job_title": "PAINTER I",
        "department": "MUSEUM OF SCIENCE & INDUSTRY",
        "base_pay": 0,
        "other_pay": 0,
        "overtime_pay": 0,
        "total_pay": 48144,
        "year": "-",
        "dept_average": 0
    },
    "1456271": {
        "first_name": "Rudy",
        "middle_name": " ",
        "last_name": "Arellanes",
        "job_title": "SUPERVISING MUSEUM SECURITY OFFICER",
        "department": "MUSEUM OF SCIENCE & INDUSTRY",
        "base_pay": 0,
        "other_pay": 0,
        "overtime_pay": 0,
        "total_pay": 48017.04,
        "year": "-",
        "dept_average": 0
    },
    "1025397": {
        "first_name": "Walter",
        "middle_name": " A ",
        "last_name": "Garcia",
        "job_title": "STAFF SERVICES ANALYST (GENERAL)",
        "department": "MUSEUM OF SCIENCE & INDUSTRY",
        "base_pay": 0,
        "other_pay": 0,
        "overtime_pay": 0,
        "total_pay": 47976,
        "year": "-",
        "dept_average": 0
    },
    "1148736": {
        "first_name": "Jesse",
        "middle_name": " ",
        "last_name": "Person",
        "job_title": "BUILDING MAINTENANCE WORKER",
        "department": "MUSEUM OF SCIENCE & INDUSTRY",
        "base_pay": 0,
        "other_pay": 0,
        "overtime_pay": 0,
        "total_pay": 47181.69,
        "year": "-",
        "dept_average": 0
    },
    "1044036": {
        "first_name": "Rico",
        "middle_name": " ",
        "last_name": "Rodriguez",
        "job_title": "MUSEUM SECURITY OFFICER",
        "department": "MUSEUM OF SCIENCE & INDUSTRY",
        "base_pay": 0,
        "other_pay": 0,
        "overtime_pay": 0,
        "total_pay": 46758.06,
        "year": "-",
        "dept_average": 0
    },
    "1041406": {
        "first_name": "Elier",
        "middle_name": " ",
        "last_name": "Lopez",
        "job_title": "ELECTRICIAN I",
        "department": "MUSEUM OF SCIENCE & INDUSTRY",
        "base_pay": 0,
        "other_pay": 0,
        "overtime_pay": 0,
        "total_pay": 46631.73,
        "year": "-",
        "dept_average": 0
    },
    "1046364": {
        "first_name": "Shonsie",
        "middle_name": " ",
        "last_name": "Island",
        "job_title": "MUSEUM SECURITY OFFICER",
        "department": "MUSEUM OF SCIENCE & INDUSTRY",
        "base_pay": 0,
        "other_pay": 0,
        "overtime_pay": 0,
        "total_pay": 46474.6,
        "year": "-",
        "dept_average": 0
    },
    "1139548": {
        "first_name": "Oscar",
        "middle_name": " ",
        "last_name": "Padilla",
        "job_title": "BUILDING MAINTENANCE WORKER",
        "department": "MUSEUM OF SCIENCE & INDUSTRY",
        "base_pay": 0,
        "other_pay": 0,
        "overtime_pay": 0,
        "total_pay": 45959.64,
        "year": "-",
        "dept_average": 0
    },
    "1100714": {
        "first_name": "Thomas",
        "middle_name": " L ",
        "last_name": "Tolliver",
        "job_title": "MUSEUM SECURITY OFFICER",
        "department": "MUSEUM OF SCIENCE & INDUSTRY",
        "base_pay": 0,
        "other_pay": 0,
        "overtime_pay": 0,
        "total_pay": 45654.56,
        "year": "-",
        "dept_average": 0
    },
    "1150850": {
        "first_name": "Michelle",
        "middle_name": " R ",
        "last_name": "Ortega",
        "job_title": "DISPATCHER-CLERK",
        "department": "MUSEUM OF SCIENCE & INDUSTRY",
        "base_pay": 0,
        "other_pay": 0,
        "overtime_pay": 0,
        "total_pay": 45546.01,
        "year": "-",
        "dept_average": 0
    },
    "1114730": {
        "first_name": "Jesus",
        "middle_name": " ",
        "last_name": "Cerda",
        "job_title": "EXHIBIT DESIGNER-INSTALLER",
        "department": "MUSEUM OF SCIENCE & INDUSTRY",
        "base_pay": 0,
        "other_pay": 0,
        "overtime_pay": 0,
        "total_pay": 45449.69,
        "year": "-",
        "dept_average": 0
    },
    "1120202": {
        "first_name": "Miguel",
        "middle_name": " A ",
        "last_name": "Valdez",
        "job_title": "EXHIBIT DESIGNER-INSTALLER",
        "department": "MUSEUM OF SCIENCE & INDUSTRY",
        "base_pay": 0,
        "other_pay": 0,
        "overtime_pay": 0,
        "total_pay": 44778.18,
        "year": "-",
        "dept_average": 0
    },
    "1125765": {
        "first_name": "Charles",
        "middle_name": " R ",
        "last_name": "Harris",
        "job_title": "CUSTODIAN SUPERVISOR III",
        "department": "MUSEUM OF SCIENCE & INDUSTRY",
        "base_pay": 0,
        "other_pay": 0,
        "overtime_pay": 0,
        "total_pay": 44649.34,
        "year": "-",
        "dept_average": 0
    },
    "1152116": {
        "first_name": "Richard",
        "middle_name": " W ",
        "last_name": "Rosser",
        "job_title": "BUILDING MAINTENANCE WORKER",
        "department": "MUSEUM OF SCIENCE & INDUSTRY",
        "base_pay": 0,
        "other_pay": 0,
        "overtime_pay": 0,
        "total_pay": 44476.41,
        "year": "-",
        "dept_average": 0
    },
    "1123487": {
        "first_name": "Marilyn",
        "middle_name": " J ",
        "last_name": "Pagan",
        "job_title": "EXHIBIT WORKER, CALIFORNIA MUSEUM OF SCIENCE AND I",
        "department": "MUSEUM OF SCIENCE & INDUSTRY",
        "base_pay": 0,
        "other_pay": 0,
        "overtime_pay": 0,
        "total_pay": 43066.55,
        "year": "-",
        "dept_average": 0
    },
    "1124895": {
        "first_name": "Donald",
        "middle_name": " ",
        "last_name": "Butler",
        "job_title": "MUSEUM SECURITY OFFICER",
        "department": "MUSEUM OF SCIENCE & INDUSTRY",
        "base_pay": 0,
        "other_pay": 0,
        "overtime_pay": 0,
        "total_pay": 42680.86,
        "year": "-",
        "dept_average": 0
    },
    "1186193": {
        "first_name": "Shannon",
        "middle_name": " S ",
        "last_name": "Domingue",
        "job_title": "DISPATCHER-CLERK",
        "department": "MUSEUM OF SCIENCE & INDUSTRY",
        "base_pay": 0,
        "other_pay": 0,
        "overtime_pay": 0,
        "total_pay": 42543.22,
        "year": "-",
        "dept_average": 0
    },
    "1127700": {
        "first_name": "Eric",
        "middle_name": " ",
        "last_name": "Cruz",
        "job_title": "EXHIBIT WORKER, CALIFORNIA MUSEUM OF SCIENCE AND I",
        "department": "MUSEUM OF SCIENCE & INDUSTRY",
        "base_pay": 0,
        "other_pay": 0,
        "overtime_pay": 0,
        "total_pay": 42530.32,
        "year": "-",
        "dept_average": 0
    },
    "1159254": {
        "first_name": "Maria",
        "middle_name": " ",
        "last_name": "Parada",
        "job_title": "CUSTODIAN",
        "department": "MUSEUM OF SCIENCE & INDUSTRY",
        "base_pay": 0,
        "other_pay": 0,
        "overtime_pay": 0,
        "total_pay": 39709.81,
        "year": "-",
        "dept_average": 0
    },
    "1290847": {
        "first_name": "Andre",
        "middle_name": " ",
        "last_name": "Hundley",
        "job_title": "CUSTODIAN",
        "department": "MUSEUM OF SCIENCE & INDUSTRY",
        "base_pay": 0,
        "other_pay": 0,
        "overtime_pay": 0,
        "total_pay": 39305.81,
        "year": "-",
        "dept_average": 0
    },
    "1231525": {
        "first_name": "Clarence",
        "middle_name": " ",
        "last_name": "Johnson",
        "job_title": "GROUNDSKEEPER",
        "department": "MUSEUM OF SCIENCE & INDUSTRY",
        "base_pay": 0,
        "other_pay": 0,
        "overtime_pay": 0,
        "total_pay": 39093.6,
        "year": "-",
        "dept_average": 0
    },
    "1310823": {
        "first_name": "Jose",
        "middle_name": " F ",
        "last_name": "Hidalgo",
        "job_title": "CUSTODIAN",
        "department": "MUSEUM OF SCIENCE & INDUSTRY",
        "base_pay": 0,
        "other_pay": 0,
        "overtime_pay": 0,
        "total_pay": 38911.92,
        "year": "-",
        "dept_average": 0
    },
    "1168638": {
        "first_name": "Aaron",
        "middle_name": " D ",
        "last_name": "Wallin",
        "job_title": "DISPATCHER-CLERK",
        "department": "MUSEUM OF SCIENCE & INDUSTRY",
        "base_pay": 0,
        "other_pay": 0,
        "overtime_pay": 0,
        "total_pay": 38126.98,
        "year": "-",
        "dept_average": 0
    },
    "1169914": {
        "first_name": "Roberta",
        "middle_name": " M ",
        "last_name": "Jennings",
        "job_title": "LIBRARY TECHNICAL ASSISTANT II",
        "department": "MUSEUM OF SCIENCE & INDUSTRY",
        "base_pay": 0,
        "other_pay": 0,
        "overtime_pay": 0,
        "total_pay": 38061,
        "year": "-",
        "dept_average": 0
    },
    "1125898": {
        "first_name": "Derrick",
        "middle_name": " L ",
        "last_name": "Carter",
        "job_title": "CUSTODIAN SUPERVISOR II",
        "department": "MUSEUM OF SCIENCE & INDUSTRY",
        "base_pay": 0,
        "other_pay": 0,
        "overtime_pay": 0,
        "total_pay": 37954.24,
        "year": "-",
        "dept_average": 0
    },
    "1214995": {
        "first_name": "Laura",
        "middle_name": " ",
        "last_name": "Love",
        "job_title": "CUSTODIAN SUPERVISOR II",
        "department": "MUSEUM OF SCIENCE & INDUSTRY",
        "base_pay": 0,
        "other_pay": 0,
        "overtime_pay": 0,
        "total_pay": 37802.94,
        "year": "-",
        "dept_average": 0
    },
    "1231156": {
        "first_name": "Earnest",
        "middle_name": " L ",
        "last_name": "Richardson",
        "job_title": "GROUNDSKEEPER",
        "department": "MUSEUM OF SCIENCE & INDUSTRY",
        "base_pay": 0,
        "other_pay": 0,
        "overtime_pay": 0,
        "total_pay": 37516.48,
        "year": "-",
        "dept_average": 0
    },
    "1322399": {
        "first_name": "Alicia",
        "middle_name": " ",
        "last_name": "Valdez",
        "job_title": "OFFICE TECHNICIAN (TYPING)",
        "department": "MUSEUM OF SCIENCE & INDUSTRY",
        "base_pay": 0,
        "other_pay": 0,
        "overtime_pay": 0,
        "total_pay": 37281.02,
        "year": "-",
        "dept_average": 0
    },
    "1213246": {
        "first_name": "Blanca",
        "middle_name": " E ",
        "last_name": "Villalobos",
        "job_title": "OFFICE TECHNICIAN (TYPING)",
        "department": "MUSEUM OF SCIENCE & INDUSTRY",
        "base_pay": 0,
        "other_pay": 0,
        "overtime_pay": 0,
        "total_pay": 37160,
        "year": "-",
        "dept_average": 0
    },
    "1245006": {
        "first_name": "Robert",
        "middle_name": " A ",
        "last_name": "Sykes",
        "job_title": "CUSTODIAN",
        "department": "MUSEUM OF SCIENCE & INDUSTRY",
        "base_pay": 0,
        "other_pay": 0,
        "overtime_pay": 0,
        "total_pay": 36864.07,
        "year": "-",
        "dept_average": 0
    },
    "1249489": {
        "first_name": "Mark",
        "middle_name": " ",
        "last_name": "Comeaux",
        "job_title": "CUSTODIAN SUPERVISOR II",
        "department": "MUSEUM OF SCIENCE & INDUSTRY",
        "base_pay": 0,
        "other_pay": 0,
        "overtime_pay": 0,
        "total_pay": 35936.26,
        "year": "-",
        "dept_average": 0
    },
    "1306075": {
        "first_name": "Martha",
        "middle_name": " ",
        "last_name": "Pedroza",
        "job_title": "CUSTODIAN",
        "department": "MUSEUM OF SCIENCE & INDUSTRY",
        "base_pay": 0,
        "other_pay": 0,
        "overtime_pay": 0,
        "total_pay": 35882.4,
        "year": "-",
        "dept_average": 0
    },
    "1274936": {
        "first_name": "Elbert",
        "middle_name": " W ",
        "last_name": "Gaddis Jr",
        "job_title": "CUSTODIAN",
        "department": "MUSEUM OF SCIENCE & INDUSTRY",
        "base_pay": 0,
        "other_pay": 0,
        "overtime_pay": 0,
        "total_pay": 34554.65,
        "year": "-",
        "dept_average": 0
    },
    "1312301": {
        "first_name": "Steven",
        "middle_name": " E ",
        "last_name": "Hubble",
        "job_title": "CUSTODIAN",
        "department": "MUSEUM OF SCIENCE & INDUSTRY",
        "base_pay": 0,
        "other_pay": 0,
        "overtime_pay": 0,
        "total_pay": 34052.75,
        "year": "-",
        "dept_average": 0
    },
    "1270673": {
        "first_name": "Lisa",
        "middle_name": " E ",
        "last_name": "Deleon",
        "job_title": "OFFICE TECHNICIAN (TYPING)",
        "department": "MUSEUM OF SCIENCE & INDUSTRY",
        "base_pay": 0,
        "other_pay": 0,
        "overtime_pay": 0,
        "total_pay": 33874.3,
        "year": "-",
        "dept_average": 0
    },
    "1173808": {
        "first_name": "Jamal",
        "middle_name": " ",
        "last_name": "Burnett",
        "job_title": "CUSTODIAN SUPERVISOR II",
        "department": "MUSEUM OF SCIENCE & INDUSTRY",
        "base_pay": 0,
        "other_pay": 0,
        "overtime_pay": 0,
        "total_pay": 33869.04,
        "year": "-",
        "dept_average": 0
    },
    "1275915": {
        "first_name": "Kenneth",
        "middle_name": " W ",
        "last_name": "Holmes",
        "job_title": "CUSTODIAN",
        "department": "MUSEUM OF SCIENCE & INDUSTRY",
        "base_pay": 0,
        "other_pay": 0,
        "overtime_pay": 0,
        "total_pay": 33852.04,
        "year": "-",
        "dept_average": 0
    },
    "1281996": {
        "first_name": "Aaron",
        "middle_name": " L ",
        "last_name": "Owens",
        "job_title": "CUSTODIAN",
        "department": "MUSEUM OF SCIENCE & INDUSTRY",
        "base_pay": 0,
        "other_pay": 0,
        "overtime_pay": 0,
        "total_pay": 33216.64,
        "year": "-",
        "dept_average": 0
    },
    "1316121": {
        "first_name": "Loretta",
        "middle_name": " L ",
        "last_name": "Lavender",
        "job_title": "CUSTODIAN",
        "department": "MUSEUM OF SCIENCE & INDUSTRY",
        "base_pay": 0,
        "other_pay": 0,
        "overtime_pay": 0,
        "total_pay": 33124.9,
        "year": "-",
        "dept_average": 0
    },
    "1262721": {
        "first_name": "Juana",
        "middle_name": " ",
        "last_name": "Delgadillo",
        "job_title": "CUSTODIAN",
        "department": "MUSEUM OF SCIENCE & INDUSTRY",
        "base_pay": 0,
        "other_pay": 0,
        "overtime_pay": 0,
        "total_pay": 33008.05,
        "year": "-",
        "dept_average": 0
    },
    "1309854": {
        "first_name": "Nina",
        "middle_name": " ",
        "last_name": "Ferguson",
        "job_title": "CUSTODIAN",
        "department": "MUSEUM OF SCIENCE & INDUSTRY",
        "base_pay": 0,
        "other_pay": 0,
        "overtime_pay": 0,
        "total_pay": 32812.95,
        "year": "-",
        "dept_average": 0
    },
    "1316127": {
        "first_name": "Patricia",
        "middle_name": " A ",
        "last_name": "Smith",
        "job_title": "CUSTODIAN",
        "department": "MUSEUM OF SCIENCE & INDUSTRY",
        "base_pay": 0,
        "other_pay": 0,
        "overtime_pay": 0,
        "total_pay": 32441.04,
        "year": "-",
        "dept_average": 0
    },
    "1307547": {
        "first_name": "George",
        "middle_name": " E ",
        "last_name": "Marroquin",
        "job_title": "CUSTODIAN",
        "department": "MUSEUM OF SCIENCE & INDUSTRY",
        "base_pay": 0,
        "other_pay": 0,
        "overtime_pay": 0,
        "total_pay": 32406.63,
        "year": "-",
        "dept_average": 0
    },
    "1027049": {
        "first_name": "Dalend",
        "middle_name": " C ",
        "last_name": "Biles",
        "job_title": "MUSEUM SECURITY OFFICER",
        "department": "MUSEUM OF SCIENCE & INDUSTRY",
        "base_pay": 0,
        "other_pay": 0,
        "overtime_pay": 0,
        "total_pay": 32270.38,
        "year": "-",
        "dept_average": 0
    },
    "1299039": {
        "first_name": "Sergio",
        "middle_name": " U ",
        "last_name": "Valladares",
        "job_title": "CUSTODIAN",
        "department": "MUSEUM OF SCIENCE & INDUSTRY",
        "base_pay": 0,
        "other_pay": 0,
        "overtime_pay": 0,
        "total_pay": 32115.62,
        "year": "-",
        "dept_average": 0
    },
    "1426119": {
        "first_name": "Roger",
        "middle_name": " ",
        "last_name": "Williams",
        "job_title": "CUSTODIAN",
        "department": "MUSEUM OF SCIENCE & INDUSTRY",
        "base_pay": 0,
        "other_pay": 0,
        "overtime_pay": 0,
        "total_pay": 32004.41,
        "year": "-",
        "dept_average": 0
    },
    "1309827": {
        "first_name": "Felipe",
        "middle_name": " ",
        "last_name": "Rosas Jr",
        "job_title": "CUSTODIAN",
        "department": "MUSEUM OF SCIENCE & INDUSTRY",
        "base_pay": 0,
        "other_pay": 0,
        "overtime_pay": 0,
        "total_pay": 31970.94,
        "year": "-",
        "dept_average": 0
    },
    "1388853": {
        "first_name": "Bernard",
        "middle_name": " L ",
        "last_name": "Smith",
        "job_title": "CUSTODIAN",
        "department": "MUSEUM OF SCIENCE & INDUSTRY",
        "base_pay": 0,
        "other_pay": 0,
        "overtime_pay": 0,
        "total_pay": 31959.6,
        "year": "-",
        "dept_average": 0
    },
    "1316115": {
        "first_name": "Paula",
        "middle_name": " R ",
        "last_name": "Gatewood",
        "job_title": "CUSTODIAN",
        "department": "MUSEUM OF SCIENCE & INDUSTRY",
        "base_pay": 0,
        "other_pay": 0,
        "overtime_pay": 0,
        "total_pay": 31316.29,
        "year": "-",
        "dept_average": 0
    },
    "1299196": {
        "first_name": "Mark",
        "middle_name": " ",
        "last_name": "Behn",
        "job_title": "CUSTODIAN",
        "department": "MUSEUM OF SCIENCE & INDUSTRY",
        "base_pay": 0,
        "other_pay": 0,
        "overtime_pay": 0,
        "total_pay": 31148.02,
        "year": "-",
        "dept_average": 0
    },
    "1316124": {
        "first_name": "Harry",
        "middle_name": " B ",
        "last_name": "Sarni",
        "job_title": "CUSTODIAN",
        "department": "MUSEUM OF SCIENCE & INDUSTRY",
        "base_pay": 0,
        "other_pay": 0,
        "overtime_pay": 0,
        "total_pay": 30588,
        "year": "-",
        "dept_average": 0
    },
    "1314347": {
        "first_name": "Mavis",
        "middle_name": " R ",
        "last_name": "Holt",
        "job_title": "CUSTODIAN",
        "department": "MUSEUM OF SCIENCE & INDUSTRY",
        "base_pay": 0,
        "other_pay": 0,
        "overtime_pay": 0,
        "total_pay": 30588,
        "year": "-",
        "dept_average": 0
    },
    "1316118": {
        "first_name": "Denise",
        "middle_name": " ",
        "last_name": "Henderson",
        "job_title": "CUSTODIAN",
        "department": "MUSEUM OF SCIENCE & INDUSTRY",
        "base_pay": 0,
        "other_pay": 0,
        "overtime_pay": 0,
        "total_pay": 30348,
        "year": "-",
        "dept_average": 0
    },
    "1308946": {
        "first_name": "Joe",
        "middle_name": " ",
        "last_name": "Hidalgo",
        "job_title": "CUSTODIAN",
        "department": "MUSEUM OF SCIENCE & INDUSTRY",
        "base_pay": 0,
        "other_pay": 0,
        "overtime_pay": 0,
        "total_pay": 30248.01,
        "year": "-",
        "dept_average": 0
    },
    "1117016": {
        "first_name": "Steven",
        "middle_name": " O ",
        "last_name": "Cardona",
        "job_title": "MUSEUM SECURITY OFFICER",
        "department": "MUSEUM OF SCIENCE & INDUSTRY",
        "base_pay": 0,
        "other_pay": 0,
        "overtime_pay": 0,
        "total_pay": 29735.34,
        "year": "-",
        "dept_average": 0
    },
    "1304983": {
        "first_name": "Patricia",
        "middle_name": " C ",
        "last_name": "Graham",
        "job_title": "CUSTODIAN",
        "department": "MUSEUM OF SCIENCE & INDUSTRY",
        "base_pay": 0,
        "other_pay": 0,
        "overtime_pay": 0,
        "total_pay": 29153.62,
        "year": "-",
        "dept_average": 0
    },
    "1416749": {
        "first_name": "Richard",
        "middle_name": " ",
        "last_name": "Tun",
        "job_title": "CUSTODIAN",
        "department": "MUSEUM OF SCIENCE & INDUSTRY",
        "base_pay": 0,
        "other_pay": 0,
        "overtime_pay": 0,
        "total_pay": 28663.04,
        "year": "-",
        "dept_average": 0
    },
    "1002918": {
        "first_name": "Adriana",
        "middle_name": " ",
        "last_name": "Vasquez",
        "job_title": "EVENTS SERVICES SUPERVISOR",
        "department": "MUSEUM OF SCIENCE & INDUSTRY",
        "base_pay": 0,
        "other_pay": 0,
        "overtime_pay": 0,
        "total_pay": 27879.36,
        "year": "-",
        "dept_average": 0
    },
    "1356886": {
        "first_name": "Betty",
        "middle_name": " T ",
        "last_name": "Biggs",
        "job_title": "CUSTODIAN",
        "department": "MUSEUM OF SCIENCE & INDUSTRY",
        "base_pay": 0,
        "other_pay": 0,
        "overtime_pay": 0,
        "total_pay": 26182.12,
        "year": "-",
        "dept_average": 0
    },
    "1108240": {
        "first_name": "Oscar",
        "middle_name": " M ",
        "last_name": "Lomeli",
        "job_title": "MUSEUM SECURITY OFFICER",
        "department": "MUSEUM OF SCIENCE & INDUSTRY",
        "base_pay": 0,
        "other_pay": 0,
        "overtime_pay": 0,
        "total_pay": 25468.69,
        "year": "-",
        "dept_average": 0
    },
    "1303589": {
        "first_name": "Diana",
        "middle_name": " M ",
        "last_name": "Ibarra",
        "job_title": "CLERK II\/SCIENCE CENTER, CALIFORNIA",
        "department": "MUSEUM OF SCIENCE & INDUSTRY",
        "base_pay": 0,
        "other_pay": 0,
        "overtime_pay": 0,
        "total_pay": 10071.39,
        "year": "-",
        "dept_average": 0
    },
    "1260093": {
        "first_name": "Carolyn",
        "middle_name": " A ",
        "last_name": "Coulter",
        "job_title": "ADMINISTRATIVE ASSISTANT I\/SCIENCE CENTER, CALIFOR",
        "department": "MUSEUM OF SCIENCE & INDUSTRY",
        "base_pay": 0,
        "other_pay": 0,
        "overtime_pay": 0,
        "total_pay": 10065.5,
        "year": "-",
        "dept_average": 0
    },
    "1409167": {
        "first_name": "Loretta",
        "middle_name": " ",
        "last_name": "Barnes",
        "job_title": "EXECUTIVE ASSISTANT TO THE DIRECTOR\/SCIENCE CENTER",
        "department": "MUSEUM OF SCIENCE & INDUSTRY",
        "base_pay": 0,
        "other_pay": 0,
        "overtime_pay": 0,
        "total_pay": 8118.9,
        "year": "-",
        "dept_average": 0
    },
    "1143175": {
        "first_name": "Jesus",
        "middle_name": " R ",
        "last_name": "Solorzano",
        "job_title": "MUSEUM SECURITY OFFICER",
        "department": "MUSEUM OF SCIENCE & INDUSTRY",
        "base_pay": 0,
        "other_pay": 0,
        "overtime_pay": 0,
        "total_pay": 3366.58,
        "year": "-",
        "dept_average": 0
    },
    "1134323": {
        "first_name": "Mario",
        "middle_name": " C ",
        "last_name": "Bickham",
        "job_title": "MUSEUM SECURITY OFFICER",
        "department": "MUSEUM OF SCIENCE & INDUSTRY",
        "base_pay": 0,
        "other_pay": 0,
        "overtime_pay": 0,
        "total_pay": 141.41,
        "year": "-",
        "dept_average": 0
    }
}